fc_xd_aaaa.py
fc_aaaa-1.0.dist-info/METADATA
fc_aaaa-1.0.dist-info/WHEEL
fc_aaaa-1.0.dist-info/top_level.txt
fc_aaaa-1.0.dist-info/RECORD
