Metadata-Version: 2.1
Name: fc-aaaa
Version: 1.0
Summary: 大数据3
Home-page: UNKNOWN
Author: 大数据3
Author-email: 2073894093@qq.com
License: UNKNOWN
Platform: UNKNOWN
